harborai/__init__.py
harborai/py.typed
harborai/api/__init__.py
harborai/api/app.py
harborai/api/client.py
harborai/api/decorators.py
harborai/api/fast_client.py
harborai/api/fast_decorators.py
harborai/api/health_check.py
harborai/api/schemas.py
harborai/api/structured.py
harborai/api/routes/__init__.py
harborai/api/routes/health.py
harborai/api/routes/logs.py
harborai/api/routes/statistics.py
harborai/api/routes/tracing.py
harborai/cli/__init__.py
harborai/cli/main.py
harborai/config/__init__.py
harborai/config/performance.py
harborai/config/settings.py
harborai/core/__init__.py
harborai/core/agently_client_pool.py
harborai/core/async_cost_tracking.py
harborai/core/background_tasks.py
harborai/core/base_plugin.py
harborai/core/cache_manager.py
harborai/core/client_manager.py
harborai/core/config_validator.py
harborai/core/cost_tracking.py
harborai/core/dynamic_pricing_manager.py
harborai/core/enhanced_error_handler.py
harborai/core/enhanced_pricing.py
harborai/core/enhanced_token_parser.py
harborai/core/exceptions.py
harborai/core/fallback.py
harborai/core/fast_structured_output.py
harborai/core/lazy_plugin_manager.py
harborai/core/models.py
harborai/core/observability.py
harborai/core/optimized_plugin_manager.py
harborai/core/parameter_cache.py
harborai/core/performance_manager.py
harborai/core/plugin_manager.py
harborai/core/pricing.py
harborai/core/retry.py
harborai/core/token_parsing.py
harborai/core/token_usage.py
harborai/core/unified_decorators.py
harborai/core/vendor_manager.py
harborai/core/alerts/__init__.py
harborai/core/alerts/alert_config_loader.py
harborai/core/alerts/alert_history.py
harborai/core/alerts/alert_manager.py
harborai/core/alerts/alert_notification_config.py
harborai/core/alerts/alert_notification_mechanism.py
harborai/core/alerts/alert_rule_config.py
harborai/core/alerts/alert_suppression_config.py
harborai/core/alerts/alert_threshold_config.py
harborai/core/alerts/alert_threshold_rules.py
harborai/core/alerts/cli.py
harborai-1.0.0.post1.dist-info/licenses/LICENSE
harborai-1.0.0.post1.dist-info/METADATA
harborai-1.0.0.post1.dist-info/WHEEL
harborai-1.0.0.post1.dist-info/entry_points.txt
harborai-1.0.0.post1.dist-info/top_level.txt
harborai-1.0.0.post1.dist-info/RECORD
