Metadata-Version: 2.4
Name: harborai
Version: 1.0.0.post1
Summary: HarborAI - 高性能AI API代理和管理平台
Author-email: HarborAI Team <team@harborai.com>
License: MIT
Keywords: ai,api,proxy,openai,anthropic,llm
Classifier: Development Status :: 5 - Production/Stable
Classifier: Intended Audience :: Developers
Classifier: License :: OSI Approved :: MIT License
Classifier: Operating System :: OS Independent
Classifier: Programming Language :: Python :: 3
Classifier: Programming Language :: Python :: 3.9
Classifier: Programming Language :: Python :: 3.10
Classifier: Programming Language :: Python :: 3.11
Classifier: Programming Language :: Python :: 3.12
Requires-Python: >=3.9
License-File: LICENSE
Requires-Dist: fastapi>=0.104.0
Requires-Dist: uvicorn[standard]>=0.24.0
Requires-Dist: pydantic>=2.5.0
Requires-Dist: httpx>=0.25.0
Requires-Dist: click>=8.1.0
Requires-Dist: typer>=0.9.0
Dynamic: license-file
